wicky_vllm-0.1.6.dist-info/licenses/LICENSE
wickyvllm/__init__.py
wickyvllm/config.py
wickyvllm/llm.py
wickyvllm/sampling_params.py
wickyvllm/engine/block_manager.py
wickyvllm/engine/llm_engine.py
wickyvllm/engine/model_runner.py
wickyvllm/engine/scheduler.py
wickyvllm/engine/sequence.py
wickyvllm/layers/activation.py
wickyvllm/layers/attention.py
wickyvllm/layers/embed_head.py
wickyvllm/layers/layernorm.py
wickyvllm/layers/linear.py
wickyvllm/layers/rotary_embedding.py
wickyvllm/layers/sampler.py
wickyvllm/models/qwen3.py
wickyvllm/utils/context.py
wickyvllm/utils/loader.py
wicky_vllm-0.1.6.dist-info/METADATA
wicky_vllm-0.1.6.dist-info/WHEEL
wicky_vllm-0.1.6.dist-info/top_level.txt
wicky_vllm-0.1.6.dist-info/RECORD
