Metadata-Version: 2.4
Name: wicky-vllm
Version: 0.1.6
Summary: a lightweight vLLM implementation built from scratch
Author: David U
License-Expression: MIT
Project-URL: Homepage, https://github.com/GeeeekExplorer/nano-vllm
Requires-Python: <3.13,>=3.10
License-File: LICENSE
Requires-Dist: torch>=2.4.0
Requires-Dist: triton>=3.0.0
Requires-Dist: transformers>=4.51.0
Requires-Dist: huggingface_hub
Requires-Dist: flashinfer>=0.2.0
Requires-Dist: xxhash
Dynamic: license-file
